{"mean":{"confidence_interval":{"confidence_level":0.95,"lower_bound":772.2609036135102,"upper_bound":911.8174366145655},"point_estimate":841.0615662494014,"standard_error":35.53362721791448},"median":{"confidence_interval":{"confidence_level":0.95,"lower_bound":600.3594332298137,"upper_bound":875.6572033898306},"point_estimate":672.20353125,"standard_error":76.5905060917655},"median_abs_dev":{"confidence_interval":{"confidence_level":0.95,"lower_bound":183.52352083920874,"upper_bound":511.34516989641753},"point_estimate":292.74258877455435,"standard_error":89.45956508643651},"slope":{"confidence_interval":{"confidence_level":0.95,"lower_bound":1064.6616932100994,"upper_bound":1206.2777356111856},"point_estimate":1141.7802490025122,"standard_error":36.17334310090741},"std_dev":{"confidence_interval":{"confidence_level":0.95,"lower_bound":321.66266372738204,"upper_bound":384.6605035366766},"point_estimate":357.07228371313437,"standard_error":16.075722908509707}}